{
  "project_info": {
    "project_number": "853832968848",
    "project_id": "baii-ccea6",
    "storage_bucket": "baii-ccea6.firebasestorage.app"
  },
  "client": [
    {
      "client_info": {
        "mobilesdk_app_id": "1:853832968848:android:4e329c8326d43ae83ec615",
        "android_client_info": {
          "package_name": "com.example.first_apk"
        }
      },
      "oauth_client": [
        {
          "client_id": "853832968848-rv2qrujfnv7ohaag8msjdmovu8pitnto.apps.googleusercontent.com",
          "client_type": 1,
          "android_info": {
            "package_name": "com.example.first_apk",
            "certificate_hash": "3745ae9eb6e1ef3b3150abf815b430f3a704d926"
          }
        },
        {
          "client_id": "853832968848-a0s0p3ng98a2fl4k5e0hmkc93d5s9mli.apps.googleusercontent.com",
          "client_type": 3
        }
      ],
      "api_key": [
        {
          "current_key": "AIzaSyAJqaSBKRmfCLXCxE-prnhCEdPHbx4SP30"
        }
      ],
      "services": {
        "appinvite_service": {
          "other_platform_oauth_client": [
            {
              "client_id": "853832968848-a0s0p3ng98a2fl4k5e0hmkc93d5s9mli.apps.googleusercontent.com",
              "client_type": 3
            }
          ]
        }
      }
    },
    {
      "client_info": {
        "mobilesdk_app_id": "1:853832968848:android:99548d61d866c7ca3ec615",
        "android_client_info": {
          "package_name": "com.maidmate.app"
        }
      },
      "oauth_client": [
        {
          "client_id": "853832968848-3ta2dermuac547q8npdclhm6g60k42m6.apps.googleusercontent.com",
          "client_type": 1,
          "android_info": {
            "package_name": "com.maidmate.app",
            "certificate_hash": "3745ae9eb6e1ef3b3150abf815b430f3a704d926"
          }
        },
        {
          "client_id": "853832968848-a0s0p3ng98a2fl4k5e0hmkc93d5s9mli.apps.googleusercontent.com",
          "client_type": 3
        }
      ],
      "api_key": [
        {
          "current_key": "AIzaSyAJqaSBKRmfCLXCxE-prnhCEdPHbx4SP30"
        }
      ],
      "services": {
        "appinvite_service": {
          "other_platform_oauth_client": [
            {
              "client_id": "853832968848-a0s0p3ng98a2fl4k5e0hmkc93d5s9mli.apps.googleusercontent.com",
              "client_type": 3
            }
          ]
        }
      }
    }
  ],
  "configuration_version": "1"
}